exarth_rest_auth/__init__.py
exarth_rest_auth/admin.py
exarth_rest_auth/app_settings.py
exarth_rest_auth/forms.py
exarth_rest_auth/jwt_auth.py
exarth_rest_auth/models.py
exarth_rest_auth/serializers.py
exarth_rest_auth/social_serializers.py
exarth_rest_auth/urls.py
exarth_rest_auth/utils.py
exarth_rest_auth/views.py
exarth_rest_auth/registration/__init__.py
exarth_rest_auth/registration/app_settings.py
exarth_rest_auth/registration/serializers.py
exarth_rest_auth/registration/urls.py
exarth_rest_auth/registration/views.py
exarth_rest_auth/tests/__init__.py
exarth_rest_auth/tests/django_urls.py
exarth_rest_auth/tests/mixins.py
exarth_rest_auth/tests/settings.py
exarth_rest_auth/tests/test_api.py
exarth_rest_auth/tests/test_serializers.py
exarth_rest_auth/tests/test_social.py
exarth_rest_auth/tests/urls.py
exarth_rest_auth-1.0.3.dist-info/LICENSE
exarth_rest_auth-1.0.3.dist-info/METADATA
exarth_rest_auth-1.0.3.dist-info/WHEEL
exarth_rest_auth-1.0.3.dist-info/top_level.txt
exarth_rest_auth-1.0.3.dist-info/RECORD
