Metadata-Version: 2.1
Name: exarth-rest-auth
Version: 1.0.3
Summary: This library is a fork of the popular django-rest-auth library, with some customizations and additional features added to suit my specific use case.
Home-page: https://github.com/saqib-devops/django-rest-auth-exarth-version
Author: Exarth
Classifier: Development Status :: 5 - Production/Stable
Classifier: License :: OSI Approved :: MIT License
Classifier: Programming Language :: Python :: 3.7
Classifier: Programming Language :: Python :: 3.8
Requires-Python: >=3.6
License-File: LICENSE
